[{"id": "money-15", "type": "money", "name": "", "value": 1, "description": ""}, {"id": "money-14", "type": "money", "name": "", "value": 14, "description": ""}, {"id": "money-13", "type": "money", "name": "", "value": 13, "description": ""}, {"id": "money-12", "type": "money", "name": "", "value": 12, "description": ""}, {"id": "money-11", "type": "money", "name": "", "value": 11, "description": ""}, {"id": "money-10", "type": "money", "name": "", "value": 10, "description": ""}, {"id": "money-9", "type": "money", "name": "", "value": 9, "description": ""}, {"id": "money-8", "type": "money", "name": "", "value": 8, "description": ""}, {"id": "money-7", "type": "money", "name": "", "value": 7, "description": ""}, {"id": "money-6", "type": "money", "name": "", "value": 6, "description": ""}, {"id": "money-5", "type": "money", "name": "", "value": 5, "description": ""}, {"id": "money-4", "type": "money", "name": "", "value": 4, "description": ""}, {"id": "money-3", "type": "money", "name": "", "value": 3, "description": ""}, {"id": "money-2", "type": "money", "name": "", "value": 2, "description": ""}, {"id": "money-0", "type": "money", "name": "", "value": 0, "description": ""}]